c_libsgm.cpython-313-x86_64-linux-musl.so
libsgm-0.5.1.dist-info/LICENSE
libsgm-0.5.1.dist-info/WHEEL
libsgm-0.5.1.dist-info/METADATA
libsgm-0.5.1.dist-info/top_level.txt
libsgm-0.5.1.dist-info/RECORD
libsgm-0.5.1.dist-info/entry_points.txt
libsgm_python/__init__.py
libsgm_python/sgm_python_parall.py
libsgm_python/sgm_python.py
libsgm_python/lr_manager.py
libsgm.libs/libstdc++-0d31ccbe.so.6.0.32
libsgm.libs/libgcc_s-a0b57c20.so.1
libsgm_c/__init__.py
