Metadata-Version: 2.2
Name: libSGM
Version: 0.5.1
Summary: libSGM is a CNES version of H.Hirschmuller Semi-Global Matching
Home-page: https://github.com/CNES/Pandora_libsgm
Author: CNES
Author-email: pandora@cnes.fr
License: Apache License 2.0
Keywords: matching,pandora,photogrammetry,correlation,DIC
Platform: any
Classifier: Development Status :: 4 - Beta
Classifier: Intended Audience :: Developers
Classifier: Intended Audience :: End Users/Desktop
Classifier: Intended Audience :: Science/Research
Classifier: Environment :: Console
Classifier: Topic :: Software Development :: Libraries :: Python Modules
Classifier: License :: OSI Approved :: Apache Software License
Classifier: Operating System :: OS Independent
Classifier: Programming Language :: Python
Requires-Python: >=3.8
License-File: LICENSE
Requires-Dist: numpy
Provides-Extra: dev
Requires-Dist: pre-commit; extra == "dev"
Requires-Dist: isort>=5.8.0; extra == "dev"
Requires-Dist: black>=21.5b0; extra == "dev"
Requires-Dist: pylint; extra == "dev"
Requires-Dist: setuptools_scm; extra == "dev"
Requires-Dist: twine; extra == "dev"
Requires-Dist: build; extra == "dev"
Requires-Dist: pytest; extra == "dev"
Requires-Dist: pytest-cov; extra == "dev"
Requires-Dist: pytest-sugar; extra == "dev"
Requires-Dist: mypy; extra == "dev"
Requires-Dist: gcovr; extra == "dev"
Requires-Dist: pybind11>=2.10.0; extra == "dev"
Requires-Dist: cibuildwheel==2.22.0; extra == "dev"
Provides-Extra: sgm-python
Requires-Dist: numba>=0.55.2; extra == "sgm-python"
Provides-Extra: docs
Requires-Dist: sphinx; extra == "docs"
Requires-Dist: sphinx_rtd_theme; extra == "docs"
Requires-Dist: sphinx_autoapi; extra == "docs"
Requires-Dist: breathe; extra == "docs"
Requires-Dist: exhale; extra == "docs"
